uniseg/__init__.py
uniseg/breaking.py
uniseg/db.py
uniseg/db_lookups.py
uniseg/derived.py
uniseg/emoji.py
uniseg/graphemecluster.py
uniseg/linebreak.py
uniseg/sentencebreak.py
uniseg/unicodedata_.py
uniseg/wordbreak.py
uniseg/wrap.py
unisegp-1.0.0.dist-info/licenses/LICENSE
unisegp-1.0.0.dist-info/METADATA
unisegp-1.0.0.dist-info/WHEEL
unisegp-1.0.0.dist-info/top_level.txt
unisegp-1.0.0.dist-info/RECORD
